transfernet/__init__.py
transfernet/datasets.py
transfernet/models.py
transfernet/plots.py
transfernet/utils.py
transfernet-0.4.2.dist-info/LICENSE
transfernet-0.4.2.dist-info/METADATA
transfernet-0.4.2.dist-info/WHEEL
transfernet-0.4.2.dist-info/top_level.txt
transfernet-0.4.2.dist-info/RECORD
